enhanced_pathlib/__init__.py
enhanced_pathlib/tests/__init__.py
enhanced_pathlib/tests/test
enhanced_pathlib/tests/test1
enhanced_pathlib/tests/test1.gz
enhanced_pathlib/tests/test1.gz.sig
enhanced_pathlib/tests/test1.sig
enhanced_pathlib/tests/test2
enhanced_pathlib/tests/test2.gz
enhanced_pathlib/tests/test_epath.py
enhanced_pathlib/tests/testpublickey.pem
enhanced_pathlib-0.0.5.dist-info/METADATA
enhanced_pathlib-0.0.5.dist-info/WHEEL
enhanced_pathlib-0.0.5.dist-info/licenses/LICENSE
enhanced_pathlib-0.0.5.dist-info/RECORD
