Metadata-Version: 2.3
Name: enhanced_pathlib
Version: 0.0.5
Summary: Enhanced Path library for python3
Project-URL: Homepage, https://github.com/kot-begemot-uk/enhanced_pathlib
Project-URL: Issues, https://github.com/kot-begemot-uk/enhanced_pathlib/issues
Author-email: Anton Ivanov <anton.ivanov@cambridgegreys.com>
License: BSD-3-Clause
Classifier: Operating System :: OS Independent
Classifier: Programming Language :: Python :: 3
Requires-Python: >=3.9
